versalaw2/__init__.py
versalaw2/ai_anhancement.py
versalaw2/ai_legal_personhood_analyzer.py
versalaw2/config.py
versalaw2/contract_analyzer.py
versalaw2/core.py
versalaw2/core_enhanced.py
versalaw2/document_processor.py
versalaw2/enhanced_database.py
versalaw2/enhanced_legal_analyzer.py
versalaw2/enhanced_search.py
versalaw2/international_digital_law_analyzer.py
versalaw2/legal_expert.py
versalaw2/maya_legal_qa_system.py
versalaw2/maya_wisdom_processor.py
versalaw2/prompt_templates.py
versalaw2/unified_analysis_engine.py
versalaw2/unified_analyzer.py
versalaw2/expert_modules/maya_legal_qa_system.py
versalaw2/legal_databases/ANALISIS_KLAUSUL_BERBAHAYA_PERJANJIAN_INTERNASIONAL.md
versalaw2/legal_databases/DATABASE_HUKUM_LENGKAP.md
versalaw2/legal_databases/DATABASE_KUHP_BARU_2026.md
versalaw2/legal_databases/DATABASE_UNIDROIT_PRINCIPLES_2016.md
versalaw2/legal_databases/KASUS_LENGKAP_DAN_GUGATAN_SEKALIGUS.md
versalaw2/legal_databases/analisis_klausul_kerahasiaan.md
versalaw2-3.0.1.dist-info/licenses/LICENSE
versalaw2-3.0.1.dist-info/METADATA
versalaw2-3.0.1.dist-info/WHEEL
versalaw2-3.0.1.dist-info/top_level.txt
versalaw2-3.0.1.dist-info/RECORD
