Metadata-Version: 2.4
Name: versalaw2
Version: 3.0.1
Summary: Advanced Indonesian Legal AI with Ghost Contract Analysis & 100+ Expert Study Cases
Author: VersaLaw Team
Author-email: Your Name <your.email@example.com>
License: MIT License
Project-URL: Homepage, https://github.com/yourusername/versalaw2
Project-URL: Documentation, https://github.com/yourusername/versalaw2#readme
Project-URL: Repository, https://github.com/yourusername/versalaw2
Project-URL: Issues, https://github.com/yourusername/versalaw2/issues
Keywords: legal,ai,indonesia,contract,analysis,law
Classifier: Development Status :: 4 - Beta
Classifier: Intended Audience :: Developers
Classifier: License :: OSI Approved :: MIT License
Classifier: Operating System :: OS Independent
Classifier: Programming Language :: Python :: 3
Classifier: Programming Language :: Python :: 3.8
Classifier: Programming Language :: Python :: 3.9
Classifier: Programming Language :: Python :: 3.10
Classifier: Programming Language :: Python :: 3.11
Classifier: Programming Language :: Python :: 3.12
Classifier: Topic :: Text Processing :: Linguistic
Requires-Python: >=3.7
License-File: LICENSE
Requires-Dist: numpy>=1.21.0
Requires-Dist: pandas>=1.3.0
Requires-Dist: scikit-learn>=1.0.0
Requires-Dist: transformers>=4.20.0
Requires-Dist: torch>=1.9.0
Requires-Dist: requests>=2.25.0
Provides-Extra: dev
Requires-Dist: pytest>=6.0; extra == "dev"
Requires-Dist: black>=22.0; extra == "dev"
Requires-Dist: flake8>=4.0; extra == "dev"
Dynamic: author
Dynamic: license-file
Dynamic: requires-python
